slack_bot_openai/__init__.py
slack_bot_openai/handler.py
slack_bot_openai-0.1.5.dist-info/METADATA
slack_bot_openai-0.1.5.dist-info/WHEEL
slack_bot_openai-0.1.5.dist-info/top_level.txt
slack_bot_openai-0.1.5.dist-info/RECORD
