Metadata-Version: 2.2
Name: slack_bot_openai
Version: 0.1.5
Summary: OpenAI-powered Slack bot framework with conversation history and thread support
Author: Bary Huang
Author-email: buryhuang@gmail.com
Requires-Python: >=3.11
Requires-Dist: openai==1.59.5
Requires-Dist: slack-bolt>=1.18.0
Requires-Dist: boto3==1.34.49
Dynamic: author
Dynamic: author-email
Dynamic: requires-dist
Dynamic: requires-python
Dynamic: summary
